SIDR-0.0.2a2.dist-info/LICENSE.txt
SIDR-0.0.2a2.dist-info/METADATA
SIDR-0.0.2a2.dist-info/RECORD
SIDR-0.0.2a2.dist-info/WHEEL
SIDR-0.0.2a2.dist-info/entry_points.txt
SIDR-0.0.2a2.dist-info/top_level.txt
sidr/__init__.py
sidr/cli.py
sidr/common.py
sidr/default.py
sidr/runfile.py
tests/test_cli.py
tests/test_common.py
tests/test_default.py
tests/test_runfile.py
