Metadata-Version: 2.1
Name: SIDR
Version: 0.0.2a2
Summary: Sequence Idenification using Decision tRees; a tool to classify DNA reads using machine learning models.
Home-page: https://github.com/damurdock/SIDR
Author: Duncan Murdock
Author-email: me@duncanmurdock.name
License: MIT
Keywords: console tool bioinformatics
Platform: UNKNOWN
Classifier: Development Status :: 3 - Alpha
Classifier: Environment :: Console
Classifier: Topic :: Scientific/Engineering :: Bio-Informatics
Classifier: License :: OSI Approved :: MIT License
Classifier: Intended Audience :: Science/Research
Requires-Dist: NumPy (<=1.14.5)
Requires-Dist: SciPy
Requires-Dist: pysam (>=0.8.1)
Requires-Dist: BioPython
Requires-Dist: scikit-learn
Requires-Dist: click
Requires-Dist: pandas
